dotquery/__init__.py
dotquery/dotquery.py
dotquery-0.1.1.dist-info/METADATA
dotquery-0.1.1.dist-info/WHEEL
dotquery-0.1.1.dist-info/top_level.txt
dotquery-0.1.1.dist-info/RECORD
