Metadata-Version: 2.4
Name: dotquery
Version: 0.1.1
Summary: A universal proxy class for Python that provides chainable, dot-notation access to nested data structures.
Author-email: gaojingyu <1121087373@qq.com>
Project-URL: Homepage, https://pypi.org/project/dotquery/
Project-URL: Bug Tracker, https://github.com/gaojingyu/dotquery/issues
Classifier: Programming Language :: Python :: 3
Classifier: License :: OSI Approved :: MIT License
Classifier: Operating System :: OS Independent
Classifier: Intended Audience :: Developers
Classifier: Topic :: Software Development :: Libraries :: Python Modules
Classifier: Topic :: Utilities
Requires-Python: >=3.8
